ai_terminal/ai_command_processor.py
ai_terminal/command_processor.py
ai_terminal/command_registry.py
ai_terminal/main.py
ai_terminal/commands/__init__.py
ai_terminal/commands/base.py
ai_terminal/commands/cat.py
ai_terminal/commands/cd.py
ai_terminal/commands/cp.py
ai_terminal/commands/df.py
ai_terminal/commands/echo.py
ai_terminal/commands/free.py
ai_terminal/commands/ls.py
ai_terminal/commands/mkdir.py
ai_terminal/commands/mv.py
ai_terminal/commands/rm.py
ai_terminal/commands/top.py
ai_terminal/commands/touch.py
ai_terminal_codemate-0.1.1.dist-info/licenses/LICENSE
ai_terminal_codemate-0.1.1.dist-info/METADATA
ai_terminal_codemate-0.1.1.dist-info/WHEEL
ai_terminal_codemate-0.1.1.dist-info/entry_points.txt
ai_terminal_codemate-0.1.1.dist-info/top_level.txt
ai_terminal_codemate-0.1.1.dist-info/RECORD
