Metadata-Version: 2.4
Name: ai-terminal-codemate
Version: 0.1.1
Summary: AI-powered terminal with natural language command support
Author: Adarsh
License-Expression: MIT
License-File: LICENSE
Requires-Dist: psutil
Requires-Dist: python-dotenv
Requires-Dist: openai>=1.0.0
Requires-Dist: google-generativeai
Dynamic: license-file
